lmrtfy/__init__.py
lmrtfy/__main__.py
lmrtfy/fetch_results.py
lmrtfy/functions.py
lmrtfy/helper.py
lmrtfy/login.py
lmrtfy/annotation/__init__.py
lmrtfy/runner/__init__.py
lmrtfy/runner/__main__.py
lmrtfy/runner/runner.py
lmrtfy/runner/timer.py
lmrtfy-0.0.13.dist-info/entry_points.txt
lmrtfy-0.0.13.dist-info/LICENSE
lmrtfy-0.0.13.dist-info/WHEEL
lmrtfy-0.0.13.dist-info/METADATA
lmrtfy-0.0.13.dist-info/RECORD
