Metadata-Version: 2.1
Name: lmrtfy
Version: 0.0.13
Summary: Turn variables into program arguments. Auto-generates a CLI interface and an API using lmrtfy.de.
Keywords: api,generator,cli
Author-email: "lmrt.fyi" <hello@lmrt.fyi>
Requires-Python: >=3.7
Classifier: License :: OSI Approved :: BSD License
Classifier: Programming Language :: Python
Classifier: Programming Language :: Python :: 3.7
Classifier: Programming Language :: Python :: 3.8
Classifier: Programming Language :: Python :: 3.8
Classifier: Programming Language :: Python :: 3.10
Classifier: Operating System :: POSIX :: Linux
Classifier: Operating System :: MacOS
Classifier: Operating System :: Microsoft :: Windows
Classifier: Intended Audience :: Developers
Classifier: Intended Audience :: Information Technology
Classifier: Intended Audience :: Science/Research
Classifier: Topic :: Scientific/Engineering
Classifier: Topic :: Software Development
Classifier: Topic :: System :: Software Distribution
Requires-Dist: certifi>=2022.5.18.1
Requires-Dist: charset-normalizer>=2.0.12
Requires-Dist: filehash>=0.2.dev1
Requires-Dist: idna>=3.3
Requires-Dist: numpy>=1.19.0
Requires-Dist: PyYAML>=6.0
Requires-Dist: requests>=2.28.0
Requires-Dist: typing_extensions>=4.2.0
Requires-Dist: urllib3>=1.26.9
Requires-Dist: paho-mqtt
Requires-Dist: fire
Requires-Dist: pyjwt
Requires-Dist: flask
Requires-Dist: werkzeug
Requires-Dist: cryptography
Requires-Dist: coloredlogs
Requires-Dist: packaging
Requires-Dist: python-daemon
Requires-Dist: makefun
Requires-Dist: shortuuid
Requires-Dist: black ; extra == "dev"
Requires-Dist: bumpver ; extra == "dev"
Requires-Dist: isort ; extra == "dev"
Requires-Dist: pip-tools ; extra == "dev"
Requires-Dist: pytest ; extra == "dev"
Requires-Dist: numpy ; extra == "dev"
Project-URL: documentation, https://lmrtfy.github.io/lmrtfy
Project-URL: homepage, https://lmrt.fyi
Project-URL: repository, https://github.com/lmrtfy/lmrtfy
Provides-Extra: dev
